tokko_rpc/__init__.py
tokko_rpc/client.py
tokko_rpc/decorators.py
tokko_rpc/exceptions.py
tokko_rpc/server.py
tokko_rpc/templates.py
tokko_rpc/tests.py
tokko_rpc/utils.py
tokko_rpc-0.0.2.dist-info/METADATA
tokko_rpc-0.0.2.dist-info/WHEEL
tokko_rpc-0.0.2.dist-info/top_level.txt
tokko_rpc-0.0.2.dist-info/RECORD
